__init__.py
setup.py
lexers/__init__.py
lexers/vdm.py
pygments_plugin_vdm_lexer.egg-info/PKG-INFO
pygments_plugin_vdm_lexer.egg-info/SOURCES.txt
pygments_plugin_vdm_lexer.egg-info/dependency_links.txt
pygments_plugin_vdm_lexer.egg-info/entry_points.txt
pygments_plugin_vdm_lexer.egg-info/top_level.txt
styles/__init__.py
styles/colorful.py
test/test.py