Metadata-Version: 1.0
Name: pygments-plugin-vdm-lexer
Version: 1.0
Summary: Pygments lexer for VDM
Home-page: https://github.com/mas0061/VDMLexer
Author: mas0061
Author-email: github@mas0061.net
License: MIT
Keywords: pygments lexer vdm
Platform: UNKNOWN
